flask_ezmail/__init__.py
flask_ezmail/connection.py
flask_ezmail/flask_mail.py
flask_ezmail/mail.py
flask_ezmail/message.py
flask_ezmail/utils.py
flask_ezmail-0.6.3.dist-info/LICENSE
flask_ezmail-0.6.3.dist-info/METADATA
flask_ezmail-0.6.3.dist-info/WHEEL
flask_ezmail-0.6.3.dist-info/top_level.txt
flask_ezmail-0.6.3.dist-info/RECORD
